{
  "collectionName": "components_artcl_trtm_just_films",
  "info": {
    "displayName": "TrioItemJustFilm"
  },
  "options": {},
  "attributes": {
    "just_filmi_article": {
      "type": "relation",
      "relation": "oneToOne",
      "target": "api::just-filmi-article.just-filmi-article"
    },
    "title": {
      "type": "string"
    },
    "lead": {
      "type": "string"
    },
    "customUrl": {
      "type": "string"
    },
    "image": {
      "type": "media",
      "allowedTypes": [
        "images"
      ]
    }
  }
}